firevizz/__init__.py
firevizz/firevizz.py
firevizz-0.1.1.dist-info/licenses/LICENSE
firevizz-0.1.1.dist-info/METADATA
firevizz-0.1.1.dist-info/WHEEL
firevizz-0.1.1.dist-info/top_level.txt
firevizz-0.1.1.dist-info/RECORD
