Metadata-Version: 2.4
Name: firevizz
Version: 0.1.1
Summary: A Python library for visualizing and analyzing fire detection data
Home-page: https://github.com/RipunjayS109/firevizz
Author: Ripunjay Singh, Deepesh Kumar Meena
Author-email: ripunjaysingh2104114@dei.ac.in, deepeshmeena0600@gmail.com
Keywords: fire detection,visualization,mapping,sensor data
Classifier: Development Status :: 4 - Beta
Classifier: Intended Audience :: Science/Research
Classifier: License :: OSI Approved :: MIT License
Classifier: Operating System :: OS Independent
Classifier: Programming Language :: Python :: 3
Classifier: Programming Language :: Python :: 3.6
Classifier: Programming Language :: Python :: 3.7
Classifier: Programming Language :: Python :: 3.8
Classifier: Programming Language :: Python :: 3.9
Classifier: Topic :: Scientific/Engineering :: Visualization
Requires-Python: >=3.6
License-File: LICENSE
Requires-Dist: pandas>=1.3.0
Requires-Dist: folium>=0.12.0
Requires-Dist: scikit-learn>=1.0.0
Requires-Dist: joblib>=1.0.0
Dynamic: author
Dynamic: author-email
Dynamic: classifier
Dynamic: description
Dynamic: description-content-type
Dynamic: home-page
Dynamic: keywords
Dynamic: license-file
Dynamic: requires-dist
Dynamic: requires-python
Dynamic: summary
